tf2show/__init__.py
tf2show/tf2show.py
tf2show-0.0.5.dist-info/LICENSE
tf2show-0.0.5.dist-info/METADATA
tf2show-0.0.5.dist-info/WHEEL
tf2show-0.0.5.dist-info/top_level.txt
tf2show-0.0.5.dist-info/RECORD
