Metadata-Version: 2.1
Name: tf2show
Version: 0.0.5
Summary: tf2show prints tensorflow2's keras model pretty.
Home-page: https://github.com/springkim/tf2show
Author: Bomm Kim
Author-email: springnode@gmail.com
License: UNKNOWN
Platform: UNKNOWN
Classifier: Programming Language :: Python :: 3
Classifier: License :: OSI Approved :: MIT License
Classifier: Operating System :: OS Independent
Requires-Python: >=3.6
Requires-Dist: openpyxl (>=3.0.0)
